aws_hexagonal_adapters/cloudwatch_service.py
aws_hexagonal_adapters/dynamo_db_service.py
aws_hexagonal_adapters/event_bridge_service.py
aws_hexagonal_adapters/s3_service.py
aws_hexagonal_adapters/ses_service.py
aws_hexagonal_adapters/sqs_service.py
aws_hexagonal_adapters/ssm_service.py
aws_hexagonal_adapters-1.4.1.dist-info/LICENSE
aws_hexagonal_adapters-1.4.1.dist-info/METADATA
aws_hexagonal_adapters-1.4.1.dist-info/WHEEL
aws_hexagonal_adapters-1.4.1.dist-info/top_level.txt
aws_hexagonal_adapters-1.4.1.dist-info/RECORD
